aiosonos/__init__.py
aiosonos/client.py
aiosonos/const.py
aiosonos/exceptions.py
aiosonos/group.py
aiosonos/player.py
aiosonos/py.typed
aiosonos/utils.py
aiosonos/api/__init__.py
aiosonos/api/_base.py
aiosonos/api/models.py
aiosonos/api/websockets.py
aiosonos/api/namespaces/__init__.py
aiosonos/api/namespaces/_base.py
aiosonos/api/namespaces/audio_clip.py
aiosonos/api/namespaces/group_volume.py
aiosonos/api/namespaces/groups.py
aiosonos/api/namespaces/home_theater.py
aiosonos/api/namespaces/playback.py
aiosonos/api/namespaces/playback_metadata.py
aiosonos/api/namespaces/playback_session.py
aiosonos/api/namespaces/player_volume.py
aiosonos-0.1.9.dist-info/LICENSE
aiosonos-0.1.9.dist-info/METADATA
aiosonos-0.1.9.dist-info/WHEEL
aiosonos-0.1.9.dist-info/top_level.txt
aiosonos-0.1.9.dist-info/RECORD
